openapscontrib.mmhistorytools-0.1.5-py2.7-nspkg.pth
openapscontrib/mmhistorytools/__init__.py
openapscontrib/mmhistorytools/historytools.py
openapscontrib/mmhistorytools/models.py
openapscontrib/mmhistorytools/version.py
openapscontrib.mmhistorytools-0.1.5.dist-info/DESCRIPTION.rst
openapscontrib.mmhistorytools-0.1.5.dist-info/METADATA
openapscontrib.mmhistorytools-0.1.5.dist-info/metadata.json
openapscontrib.mmhistorytools-0.1.5.dist-info/namespace_packages.txt
openapscontrib.mmhistorytools-0.1.5.dist-info/RECORD
openapscontrib.mmhistorytools-0.1.5.dist-info/top_level.txt
openapscontrib.mmhistorytools-0.1.5.dist-info/WHEEL
