Metadata-Version: 2.0
Name: openapscontrib.mmhistorytools
Version: 0.1.5
Summary: openaps mmhistorytools plugin
Home-page: https://github.com/loudnate/openaps-mmhistorytools
Author: Nathan Racklyeft
Author-email: loudnate+pypi@gmail.com
License: MIT
Download-URL: http://pypi.python.org/pypi/openapscontrib.mmhistorytools
Platform: any
Classifier: Development Status :: 3 - Alpha
Classifier: Environment :: Console
Classifier: Intended Audience :: Developers
Classifier: License :: OSI Approved :: MIT License
Classifier: Operating System :: OS Independent
Classifier: Programming Language :: Python :: 2.7
Classifier: Topic :: Documentation
Classifier: Topic :: Utilities
Requires-Dist: openaps
Requires-Dist: python-dateutil
